AUTHORS.md
CONTRIBUTING.md
LICENSE
MANIFEST.in
README.md
RELEASING.md
_mpld3_setup.py
setup.cfg
setup.py
version.py
examples/custom_plugin.py
examples/drag_points.py
examples/heart_path.py
examples/html_tooltips.py
examples/interactive_legend.py
examples/linked_brush.py
examples/mouse_position.py
examples/mpld3_logo.py
examples/random_walk.py
examples/scatter_tooltip.py
mpld3/__about__.py
mpld3/__init__.py
mpld3/_display.py
mpld3/_server.py
mpld3/mpld3renderer.py
mpld3/plugins.py
mpld3/urls.py
mpld3/utils.py
mpld3/js/d3.v3.min.js
mpld3/js/mpld3.v0.3git.js
mpld3/js/mpld3.v0.3git.min.js
mpld3/mplexporter/__init__.py
mpld3/mplexporter/_py3k_compat.py
mpld3/mplexporter/exporter.py
mpld3/mplexporter/tools.py
mpld3/mplexporter/utils.py
mpld3/mplexporter/renderers/__init__.py
mpld3/mplexporter/renderers/base.py
mpld3/mplexporter/renderers/fake_renderer.py
mpld3/mplexporter/renderers/vega_renderer.py
mpld3/mplexporter/renderers/vincent_renderer.py
mpld3/mplexporter/tests/__init__.py
mpld3/mplexporter/tests/test_basic.py
mpld3/mplexporter/tests/test_utils.py
mpld3/test_plots/__init__.py
mpld3/test_plots/test_axis.py
mpld3/test_plots/test_contour.py
mpld3/test_plots/test_contourf.py
mpld3/test_plots/test_date.py
mpld3/test_plots/test_errorbar.py
mpld3/test_plots/test_fill.py
mpld3/test_plots/test_hist.py
mpld3/test_plots/test_imshow.py
mpld3/test_plots/test_inf.py
mpld3/test_plots/test_interactive_legend.py
mpld3/test_plots/test_legend.py
mpld3/test_plots/test_legend_scatter.py
mpld3/test_plots/test_line_HTMLtooltips.py
mpld3/test_plots/test_line_collections.py
mpld3/test_plots/test_line_tooltips.py
mpld3/test_plots/test_lines.py
mpld3/test_plots/test_logscale.py
mpld3/test_plots/test_markers.py
mpld3/test_plots/test_mouse_events.py
mpld3/test_plots/test_nan.py
mpld3/test_plots/test_pandas_timeaxis.py
mpld3/test_plots/test_patches.py
mpld3/test_plots/test_subplots.py
mpld3/test_plots/test_text.py
mpld3/test_plots/test_tooltips_basic.py
pycbc_mpld3.egg-info/PKG-INFO
pycbc_mpld3.egg-info/SOURCES.txt
pycbc_mpld3.egg-info/dependency_links.txt
pycbc_mpld3.egg-info/top_level.txt