Metadata-Version: 1.1
Name: pycbc-mpld3
Version: 0.3.dev0
Summary: D3 Viewer for Matplotlib
Home-page: http://mpld3.github.com
Author: Jake VanderPlas
Author-email: jakevdp@cs.washington.edu
License: BSD 3-clause
Download-URL: http://github.com/jakevdp/mpld3
Platform: UNKNOWN
Classifier: Development Status :: 4 - Beta
Classifier: Environment :: Console
Classifier: Intended Audience :: Science/Research
Classifier: License :: OSI Approved :: BSD License
Classifier: Natural Language :: English
Classifier: Programming Language :: Python :: 2.6
Classifier: Programming Language :: Python :: 2.7
Classifier: Programming Language :: Python :: 3.3
Classifier: Programming Language :: Python :: 3.4
